microfading/MFT_info_dictionaries.py
microfading/MFT_info_templates.py
microfading/__init__.py
microfading/blank_rectangle.png
microfading/colour_circle.png
microfading/config.py
microfading/config_info.json
microfading/microfading.py
microfading/plotting.py
microfading/process_rawfiles.py
microfading/datasets/2024-144 BWS0024 G01 BW1_01-spect.txt
microfading/datasets/2024-144 BWS0024 G01 BW1_01-spect_convert.txt
microfading/datasets/2024-144 BWS0024 G01 BW1_01.rfc
microfading/datasets/2024-144 BWS0024 G01 BW1_01.txt
microfading/datasets/2024-144_BWS0024_04_G02_BW1_c01_000001.txt
microfading/datasets/2024-144_MF.BWS0024.01_G01_BW1_reference_2024-07-30_MFT2.xlsx
microfading/datasets/2024-144_MF.BWS0024.04_G02_BW1_reference_2024-08-02_MFT1.xlsx
microfading/datasets/2024-144_MF.BWS0024.G01_avg_BW1_reference_2024-07-30_MFT2.xlsx
microfading/datasets/2024-144_MF.BWS0025.01_G01_BW2_reference_2024-08-02_MFT2.xlsx
microfading/datasets/2024-144_MF.BWS0025.04_G02_BW2_reference_2024-08-02_MFT1.xlsx
microfading/datasets/2024-144_MF.BWS0025.G01_avg_BW2_reference_2024-08-02_MFT2.xlsx
microfading/datasets/2024-144_MF.BWS0026.01_G01_BW3_reference_2024-08-07_MFT2.xlsx
microfading/datasets/2024-144_MF.BWS0026.04_G02_BW3_reference_2024-08-02_MFT1.xlsx
microfading/datasets/2024-144_MF.BWS0026.G01_avg_BW3_reference_2024-08-07_MFT2.xlsx
microfading/datasets/2024-144_MF.dayflower4.G01_avg_0h_model_2024-07-30_MFT2.xlsx
microfading/datasets/2024-144_MF.indigo3.G01_avg_0h_model_2024-08-02_MFT2.xlsx
microfading/datasets/2024-144_MF.vermillon.01_G01_red_model_2024-07-31_MFT1.xlsx
microfading/datasets/2024-144_MF.vermillon3.01_G01_0h_model_2024-07-31_MFT2.xlsx
microfading/datasets/2024-144_MF.yellowwood.01_G01_yellow_model_2024-08-01_MFT1.xlsx
microfading/datasets/2024-144_MF.yellowwood4.01_G01_0h_model_2024-08-01_MFT2.xlsx
microfading/datasets/2024-144_yellowwood_01_G01_yellow_c01_000001.txt
microfading/datasets/2024-8200 P-001 G01 uncleaned_01-spect.txt
microfading-2.1.1.dist-info/licenses/LICENSE
microfading-2.1.1.dist-info/METADATA
microfading-2.1.1.dist-info/WHEEL
microfading-2.1.1.dist-info/top_level.txt
microfading-2.1.1.dist-info/RECORD
