Metadata-Version: 2.4
Name: microfading
Version: 2.1.1
Summary: Package to manipulate microfading data
Author: Gauthier Patin
Author-email: Gauthier Patin <g.patin@monemail.com>
License:                     GNU GENERAL PUBLIC LICENSE
Project-URL: Homepage, https://github.com/g-patin/microfading
Keywords: microfading,light-induced colour change,accelerated ageing
Classifier: Programming Language :: Python :: 3
Classifier: License :: OSI Approved :: GNU General Public License v3 (GPLv3)
Classifier: Operating System :: OS Independent
Requires-Python: >=3.8
License-File: LICENSE
Requires-Dist: colour-science
Requires-Dist: great-tables
Requires-Dist: h5py
Requires-Dist: imageio
Requires-Dist: ipywidgets
Requires-Dist: matplotlib
Requires-Dist: matplotlib_scalebar
Requires-Dist: msdb
Requires-Dist: pillow
Requires-Dist: pandas
Requires-Dist: openpyxl
Requires-Dist: jupyterlab
Requires-Dist: seaborn
Requires-Dist: scipy
Requires-Dist: uncertainties
Requires-Dist: xarray
Dynamic: license-file
